mlhelper/__init__.py
mlhelper/core.py
mlhelper_stark-0.1.0.dist-info/licenses/LICENSE.txt
mlhelper_stark-0.1.0.dist-info/METADATA
mlhelper_stark-0.1.0.dist-info/WHEEL
mlhelper_stark-0.1.0.dist-info/top_level.txt
mlhelper_stark-0.1.0.dist-info/RECORD
