Metadata-Version: 2.4
Name: mlhelper-stark
Version: 0.1.0
Summary: A simple machine learning helper module
Author-email: Sumanbabu S <sumanbabu368@gmail.com>
License: MIT
Requires-Python: >=3.8
License-File: LICENSE.txt
Requires-Dist: pandas
Requires-Dist: scikit-learn
Requires-Dist: joblib
Dynamic: license-file
